{
  "id": "bai-ru",
  "title": "Шкала тревоги Бека (BAI)",
  "description": "Опросник из 21 пункта для оценки выраженности симптомов тревоги, особенно телесных.",
  "language": "ru",
  "author": "Aaron T. Beck",
  "category": "anxiety",
  "estimatedMinutes": 5,
  "ui": {
    "inputMode": "buttons"
  },
  "instructions": {
    "title": "Инструкция",
    "text": "Ниже приведён список распространённых симптомов тревоги. Укажите, насколько сильно вас беспокоил каждый из них за последнюю неделю, включая сегодняшний день."
  },
  "scale": {
    "type": "likert",
    "min": 0,
    "max": 3,
    "options": [
      { "value": 0, "label": "Совсем не беспокоило" },
      { "value": 1, "label": "Слабо (почти не беспокоило)" },
      { "value": 2, "label": "Умеренно (было неприятно, но терпимо)" },
      { "value": 3, "label": "Сильно (едва мог(ла) это вынести)" }
    ]
  },
  "questions": [
    { "id": "q1", "number": 1, "text": "Онемение или покалывание" },
    { "id": "q2", "number": 2, "text": "Ощущение жара" },
    { "id": "q3", "number": 3, "text": "Слабость или неустойчивость в ногах" },
    { "id": "q4", "number": 4, "text": "Неспособность расслабиться" },
    { "id": "q5", "number": 5, "text": "Страх, что случится худшее" },
    { "id": "q6", "number": 6, "text": "Головокружение или ощущение лёгкости в голове" },
    { "id": "q7", "number": 7, "text": "Сильное сердцебиение" },
    { "id": "q8", "number": 8, "text": "Неустойчивость" },
    { "id": "q9", "number": 9, "text": "Чувство ужаса или сильного страха" },
    { "id": "q10", "number": 10, "text": "Нервозность" },
    { "id": "q11", "number": 11, "text": "Ощущение удушья" },
    { "id": "q12", "number": 12, "text": "Дрожь в руках" },
    { "id": "q13", "number": 13, "text": "Тряска или дрожание тела" },
    { "id": "q14", "number": 14, "text": "Страх потерять контроль" },
    { "id": "q15", "number": 15, "text": "Трудности с дыханием" },
    { "id": "q16", "number": 16, "text": "Страх смерти" },
    { "id": "q17", "number": 17, "text": "Испуг" },
    { "id": "q18", "number": 18, "text": "Расстройство желудка или дискомфорт в животе" },
    { "id": "q19", "number": 19, "text": "Обморочное состояние или головокружение" },
    { "id": "q20", "number": 20, "text": "Покраснение лица" },
    { "id": "q21", "number": 21, "text": "Потоотделение (не связанное с жарой)" }
  ],
  "scoring": {
    "method": "sum",
    "trait": "anxiety",
    "directItems": [1,2,3,4,5,6,7,8,9,10,11,12,13,14,15,16,17,18,19,20,21],
    "reverseItems": [],
    "minScore": 0,
    "maxScore": 63,
    "higherMeans": "higher_anxiety",
    "showAverage": false,
    "interpretationMode": "bands",
    "percentileBasis": "total"
  },
  "resultBands": [
    { "key": "minimal", "min": 0, "max": 7, "label": "Минимальная тревога" },
    { "key": "mild", "min": 8, "max": 15, "label": "Лёгкая тревога" },
    { "key": "moderate", "min": 16, "max": 25, "label": "Умеренная тревога" },
    { "key": "severe", "min": 26, "max": 63, "label": "Высокая тревога" }
  ],
  "resultDescription": "Этот опросник оценивает выраженность симптомов тревоги, особенно телесных (физических) проявлений. Более высокий суммарный балл указывает на более выраженную тревогу. Результат не является диагнозом, но может помочь лучше понять ваше текущее состояние и при необходимости обратиться за профессиональной помощью."
}